LICENSE
MANIFEST.in
README.md
setup.py
tapioca_desk/__init__.py
tapioca_desk/tapioca_desk.py
tapioca_desk.egg-info/PKG-INFO
tapioca_desk.egg-info/SOURCES.txt
tapioca_desk.egg-info/dependency_links.txt
tapioca_desk.egg-info/not-zip-safe
tapioca_desk.egg-info/requires.txt
tapioca_desk.egg-info/top_level.txt
tapioca_desk/resource_mapping/__init__.py
tapioca_desk/resource_mapping/cases.py
tapioca_desk/resource_mapping/companies.py
tapioca_desk/resource_mapping/customers.py
tapioca_desk/resource_mapping/labels.py