Metadata-Version: 1.1
Name: tapioca-desk
Version: 0.1
Summary: desk API wrapper using tapioca
Home-page: https://github.com/medeirosthiago/tapioca-desk
Author: Thiago Medeiros
Author-email: thsouzza@gmail.com
License: MIT
Keywords: desk python tapioca wrapper
Platform: UNKNOWN
Classifier: Development Status :: 5 - Production/Stable
Classifier: Intended Audience :: Developers
Classifier: License :: OSI Approved :: MIT License
Classifier: Natural Language :: English
Classifier: Programming Language :: Python :: 2
Classifier: Programming Language :: Python :: 2.7
Classifier: Programming Language :: Python :: 3
Classifier: Programming Language :: Python :: 3.1
Classifier: Programming Language :: Python :: 3.2
Classifier: Programming Language :: Python :: 3.3
Classifier: Programming Language :: Python :: 3.4
Classifier: Programming Language :: Python :: 3.5
Classifier: Programming Language :: Python :: 3.6
